stc8isp/stc8isp.py
stc8isp-0.3.1.dist-info/LICENSE
stc8isp-0.3.1.dist-info/METADATA
stc8isp-0.3.1.dist-info/WHEEL
stc8isp-0.3.1.dist-info/entry_points.txt
stc8isp-0.3.1.dist-info/top_level.txt
stc8isp-0.3.1.dist-info/RECORD
